advanced/__init__.py
advanced/generative_models.py
advanced/inverse_design.py
advanced/quantum_chemistry.py
api/__init__.py
api/models.py
api/server.py
cli/__init__.py
cli/main.py
core/__init__.py
core/base.py
core/constants.py
core/structure.py
database/__init__.py
database/api_clients.py
database/client.py
database/file_parsers.py
database/materials.py
database/materials_project.py
database/models.py
database/molecules.py
database/optimized_database_engine.py
database/parallel_loader.py
database/polymers.py
dft/__init__.py
dft/calculator.py
dft/kohn_sham.py
dft/pseudopotential.py
dft/pseudopotentials.py
dft/xc_functionals.py
discovery/__init__.py
discovery/active_learning.py
discovery/agents.py
discovery/bayesian.py
discovery/genetic.py
gui/README.md
gui/frontend/package.json
jupyter/__init__.py
jupyter/widgets.py
materials_simpro-1.0.0.dist-info/licenses/LICENSE
md/__init__.py
md/barostats.py
md/calculator.py
md/integrators.py
md/thermostats.py
ml/__init__.py
ml/calculator.py
ml/graph_networks.py
ml/neural_potentials.py
properties/__init__.py
properties/elastic.py
properties/electronic.py
properties/phonon.py
materials_simpro-1.0.0.dist-info/METADATA
materials_simpro-1.0.0.dist-info/WHEEL
materials_simpro-1.0.0.dist-info/entry_points.txt
materials_simpro-1.0.0.dist-info/top_level.txt
materials_simpro-1.0.0.dist-info/RECORD
