Metadata-Version: 2.4
Name: materials-simpro
Version: 1.0.0
Summary: DFT simulation package with complete human knowledge database
Author-email: Materials-SimPro Team <materials-simpro@example.com>
Maintainer-email: Materials-SimPro Team <materials-simpro@example.com>
License: MIT
Project-URL: Homepage, https://github.com/Yatrogenesis/Materials-SimPro
Project-URL: Documentation, https://github.com/Yatrogenesis/Materials-SimPro/wiki
Project-URL: Repository, https://github.com/Yatrogenesis/Materials-SimPro.git
Project-URL: Bug Tracker, https://github.com/Yatrogenesis/Materials-SimPro/issues
Project-URL: Changelog, https://github.com/Yatrogenesis/Materials-SimPro/blob/master/CHANGELOG.md
Keywords: dft,chemistry,materials,simulation,database,computational-chemistry,quantum-mechanics,molecular-dynamics
Classifier: Development Status :: 4 - Beta
Classifier: Intended Audience :: Science/Research
Classifier: Topic :: Scientific/Engineering :: Chemistry
Classifier: Topic :: Scientific/Engineering :: Physics
Classifier: License :: OSI Approved :: MIT License
Classifier: Programming Language :: Python :: 3
Classifier: Programming Language :: Python :: 3.8
Classifier: Programming Language :: Python :: 3.9
Classifier: Programming Language :: Python :: 3.10
Classifier: Programming Language :: Python :: 3.11
Classifier: Programming Language :: Python :: 3.12
Classifier: Operating System :: OS Independent
Requires-Python: >=3.8
License-File: LICENSE
Requires-Dist: numpy>=1.24.0
Requires-Dist: scipy>=1.10.0
Requires-Dist: requests>=2.28.0
Requires-Dist: tqdm>=4.65.0
Provides-Extra: dev
Requires-Dist: pytest>=7.4.0; extra == "dev"
Requires-Dist: pytest-cov>=4.1.0; extra == "dev"
Requires-Dist: black>=23.11.0; extra == "dev"
Requires-Dist: isort>=5.12.0; extra == "dev"
Requires-Dist: flake8>=6.1.0; extra == "dev"
Requires-Dist: mypy>=1.7.0; extra == "dev"
Provides-Extra: docs
Requires-Dist: sphinx>=7.2.0; extra == "docs"
Requires-Dist: sphinx-rtd-theme>=1.3.0; extra == "docs"
Requires-Dist: nbsphinx>=0.9.3; extra == "docs"
Provides-Extra: gpu
Requires-Dist: cupy-cuda12x>=12.3.0; extra == "gpu"
Provides-Extra: all
Requires-Dist: pytest>=7.4.0; extra == "all"
Requires-Dist: pytest-cov>=4.1.0; extra == "all"
Requires-Dist: black>=23.11.0; extra == "all"
Requires-Dist: matplotlib>=3.7.0; extra == "all"
Requires-Dist: plotly>=5.14.0; extra == "all"
Dynamic: license-file
